al360_taiwidgets/__init__.py
al360_taiwidgets/__version__.py
al360_taiwidgets/constants.py
al360_taiwidgets/dashboard.py
al360_taiwidgets/error_analysis_constants.py
al360_taiwidgets/error_analysis_dashboard.py
al360_taiwidgets/error_analysis_dashboard_input.py
al360_taiwidgets/error_handling.py
al360_taiwidgets/explanation_constants.py
al360_taiwidgets/explanation_dashboard.py
al360_taiwidgets/explanation_dashboard_input.py
al360_taiwidgets/fairness_dashboard.py
al360_taiwidgets/fairness_metric_calculation.py
al360_taiwidgets/interfaces.py
al360_taiwidgets/model_analysis_dashboard.py
al360_taiwidgets/model_performance_dashboard.py
al360_taiwidgets/responsibleai_dashboard.py
al360_taiwidgets/responsibleai_dashboard_input.py
al360_taiwidgets/widget/3rdpartylicenses.txt
al360_taiwidgets/widget/favicon.ico
al360_taiwidgets/widget/index.html
al360_taiwidgets/widget/main.44959db93b9f59dff9b6.esm.js
al360_taiwidgets/widget/main.44959db93b9f59dff9b6.esm.js.LICENSE.txt
al360_taiwidgets/widget/polyfills.2df2e8ae7005c1bbf442.esm.js
al360_taiwidgets/widget/runtime.28c323bf8ee123f67bad.esm.js
al360_taiwidgets-0.0.2.dist-info/LICENSE
al360_taiwidgets-0.0.2.dist-info/METADATA
al360_taiwidgets-0.0.2.dist-info/WHEEL
al360_taiwidgets-0.0.2.dist-info/top_level.txt
al360_taiwidgets-0.0.2.dist-info/RECORD
